Workbook

Sheet 事件总表（增强版）
A1: 事件名称 | B1: 类型 | C1: 发生日期 | D1: 窗口开始 (相对天数) | E1: 窗口结束 (相对天数) | F1: 影响强度 | G1: 影响方向 | H1: 影响公司/行业 | I1: 影响描述 | J1: AR/CAR量化提示 | K1: 数据来源
A2: 央行降准降息与A股大金融板块联动 | B2: 宏观/地缘 | C2: 2024-09-24 | D2: -1 | E2: 3 | F2: 中 | G2: 正面 | H2: 银行、券商、金融权重股 | I2: 央行等宣布降准降息、下调存量房贷利率，A股大金融板块集体走强，成交额急剧放大，呈现政策托底-流动性注入-风险偏好提升传导路径 | J2: 计算A股相关板块指数CAR；用事件窗口期前120天为估计期拟合收益模型 | K2: https://www.yicai.com/news/102284728.html
A3: 红海危机与A股航运板块联动 | B3: 宏观/地缘 | C3: 2023-12-18 | D3: -1 | E3: 3 | F3: 中 | G3: 正面 | H3: 航运、港口、集装箱制造 | I3: 红海危机扰乱全球航运，40英尺集装箱运输成本一月内翻番，A股航运及港口板块阶段性爆发 | J3: 计算A股相关板块指数CAR；用事件窗口期前120天为估计期拟合收益模型 | K3: https://m.yicai.com/news/101967189.html
A4: 镓锗出口管制与A股稀有金属板块联动 | B4: 宏观/地缘 | C4: 2023-07-03 | D4: -1 | E4: 3 | F4: 中 | G4: 正面 | H4: 云南锗业等小金属、有色金属板块 | I4: 商务部及海关总署对镓、锗实施出口管制，小金属概念股开盘涨停，呈现出口管制-供给收缩预期-战略资源重估路径 | J4: 计算A股相关板块指数CAR；用事件窗口期前120天为估计期拟合收益模型 | K4: https://zhishifenzi.blog.caixin.com/archives/269243
A5: 锑及超硬材料出口管制与A股锑矿板块联动 | B5: 宏观/地缘 | C5: 2024-08-15 | D5: -1 | E5: 3 | F5: 中 | G5: 正面 | H5: 华钰矿业等锑矿龙头、有色金属板块 | I5: 商务部与海关总署对锑及超硬材料实施出口管制，锑矿龙头迅速走强，有色金属板块逆势拉升 | J5: 计算A股相关板块指数CAR；用事件窗口期前120天为估计期拟合收益模型 | K5: https://www.yicai.com/news/102233191.html
A6: 超长期特别国债首发与A股基建板块联动 | B6: 宏观/地缘 | C6: 2024-05-17 | D6: -1 | E6: 3 | F6: 低 | G6: 正面 | H6: 大基建、节能环保、水利工程板块 | I6: 财政部启动首只超长期特别国债招标，A股大基建板块走强，节能环保及水利工程细分领域获资金青睐 | J6: 计算A股相关板块指数CAR；用事件窗口期前120天为估计期拟合收益模型 | K6: https://opinion.caixin.com/2024-05-20/102198056.html
A7: 日本福岛核污染水排海与A股水产养殖联动 | B7: 宏观/地缘 | C7: 2023-08-24 | D7: -1 | E7: 3 | F7: 高 | G7: 正面 | H7: 水产养殖、淡水鱼概念、内陆盐业 | I7: 日本启动福岛核污水排海，导致多国暂停进口日本水产，A股水产养殖及淡水鱼概念股全线爆发 | J7: 计算A股相关板块指数CAR；用事件窗口期前120天为估计期拟合收益模型 | K7: https://international.caixin.com/2021-04-13/101690418.html
A8: 低空经济写入政府工作报告与飞行汽车板块联动 | B8: 宏观/地缘 | C8: 2024-03-29 | D8: -1 | E8: 3 | F8: 中 | G8: 正面 | H8: 飞行汽车、整机制造、空管系统 | I8: 低空经济首次写入政府工作报告，多地跟进支持政策，飞行汽车及概念股短期涨幅翻倍 | J8: 计算A股相关板块指数CAR；用事件窗口期前120天为估计期拟合收益模型 | K8: https://www.yicai.com/news/102046696.html
A9: 中央汇金买入ETF与A股宽基指数联动 | B9: 宏观/地缘 | C9: 2023-10-24 | D9: -1 | E9: 3 | F9: 低 | G9: 正面 | H9: 沪深300ETF、券商、高股息央企 | I9: 中央汇金公开买入ETF并表示继续增持，沪深300ETF成交量急剧放大，券商及央企板块止跌企稳 | J9: 计算A股相关板块指数CAR；用事件窗口期前120天为估计期拟合收益模型 | K9: https://finance.caixin.com/2023-10-24/102119797.html
A10: 中东地缘局势升级与A股避险板块联动 | B10: 宏观/地缘 | C10: 2024-04-15 | D10: -1 | E10: 3 | F10: 中 | G10: 正面 | H10: 黄金股、国防军工板块 | I10: 中东冲突升级推升避险情绪，国际金价大幅波动，A股黄金股逆势拉升，军工板块资金涌入 | J10: 计算A股相关板块指数CAR；用事件窗口期前120天为估计期拟合收益模型 | K10: https://www.yicai.com/news/103075913.html
A11: CrowdStrike全球宕机与A股网安板块联动 | B11: 宏观/地缘 | C11: 2024-07-19 | D11: -1 | E11: 3 | F11: 中 | G11: 正面 | H11: 网络安全、信创板块 | I11: CrowdStrike更新失误导致全球微软系统蓝屏，A股网络安全及信创板块迅速拉升，国产网安龙头大幅走高 | J11: 计算A股相关板块指数CAR；用事件窗口期前120天为估计期拟合收益模型 | K11: https://www.yicai.com/news/102199222.html
A12: 中国对6国单方面免签与A股旅游航空联动 | B12: 宏观/地缘 | C12: 2023-11-24 | D12: -1 | E12: 3 | F12: 低 | G12: 正面 | H12: 旅行社、航空、机场板块 | I12: 中国对法、德等6国试行单方面免签，入境游旅行社个股活跃，航空股及机场获实质性利好 | J12: 计算A股相关板块指数CAR；用事件窗口期前120天为估计期拟合收益模型 | K12: https://international.caixin.com/2023-11-24/102139087.html
A13: 欧盟对华电动车反补贴调查与A股汽车出海联动 | B13: 宏观/地缘 | C13: 2023-10-04 | D13: -1 | E13: 3 | F13: 低 | G13: 负面 | H13: 整车板块（短期承压）、海外布局汽车零部件企业 | I13: 欧盟对中国纯电动汽车启动反补贴调查，整车板块短期承压，已在海外布局产能的零部件企业获长线资金逆势加仓 | J13: 计算A股相关板块指数CAR；用事件窗口期前120天为估计期拟合收益模型 | K13: https://m.caixin.com/m/2023-10-11/102115853.html
... A100: 潍柴动力一季报预增大幅提振商用车 | B100: 公司行为 | C100: 2024-04-08 | D100: -1 | E100: 3 | F100: 中 | G100: 正面 | H100: 潍柴动力、重卡整车、汽车零部件 | I100: 重卡出口强劲及燃气车市占率提升带来利润大增，验证商用车行业景气拐点，带动相关零部件及整车上扬 | J100: 对比关联个股与行业指数；计算窗口期内超额收益AR | K100: https://stcn.com/article/detail/3563922.html

Sheet Python分析模板
A1: # ============================================================
A2: # 事件研究分析模板 (Event Study - AR / CAR 计算框架)
A3: # ============================================================
A4: import pandas as pd
A5: import numpy as np
A6: from datetime import timedelta
A8: # 1. 读入事件表
A9: df_events = pd.read_excel("事件整理总表（增强版）.xlsx", sheet_name="事件总表（增强版）")
A10: df_events["发生日期"] = pd.to_datetime(df_events["发生日期"])
A12: # 2. 读入股价数据（示例结构）
A13: # df_prices: columns = ['date', 'ticker', 'close', 'return']
A14: df_prices = pd.read_csv("stock_prices.csv", parse_dates=["date"])
... A83: df_car.to_excel("event_study_results.xlsx", index=False)

Sheet 字段说明
A1: 字段名 | B1: 含义 | C1: 可选值 / 示例
A2: 发生日期 | B2: 事件正式公告或发生的日期 | C2: YYYY-MM-DD
A3: 窗口开始（相对天数） | B3: 事件窗口相对于发生日期的起始偏移（交易日） | C3: -1 表示事件前1天
A4: 窗口结束（相对天数） | B4: 事件窗口相对于发生日期的结束偏移（交易日） | C4: +3 表示事件后3天
A5: 影响强度 | B5: 对股市影响的定性估计 | C5: 高 / 中 / 低
A6: 影响方向 | B6: 事件对目标板块的方向 | C6: 正面 / 负面 / 双向
A7: AR/CAR量化提示 | B7: 说明如何在Python中对该事件计算异常收益 | C7: 见Python分析模板
A8: 类型 | B8: 事件大类 | C8: 宏观/地缘 / 行业/技术 / 政策

Sheet 特征矩阵
A1: 序号 | B1: 事件名称 | C1: 类型 | D1: 发生日期 | E1: 窗口开始 | F1: 窗口结束 | G1: 窗口长度 | H1: 影响强度 | I1: 强度得分 | J1: 影响方向 | K1: 方向得分 | L1: 综合影响得分 | M1: 宏观/地缘 | N1: 行业/技术 | O1: 政策 | P1: 新闻发布量（待填） | Q1: 舆情热度（待填） | R1: 情感倾向（待填） | S1: 代理CAR(%)（已填，待行情核验） | T1: 数据完整性
A2: =IF('事件总表（增强版）'!A2="","",ROW()-1) -> 1 | B2: =IF('事件总表（增强版）'!A2="","",'事件总表（增强版）'!A2) -> 央行降准降息与A股大金融板块联动 | C2: =IF('事件总表（增强版）'!B2="","",'事件总表（增强版）'!B2) -> 宏观/地缘 | D2: =IF('事件总表（增强版）'!C2="","",'事件总表（增强版）'!C2) -> 2024-09-24 | E2: =IF('事件总表（增强版）'!D2="","",'事件总表（增强版）'!D2) -> -1 | F2: =IF('事件总表（增强版）'!E2="","",'事件总表（增强版）'!E2) -> 3 | G2: =IF('事件总表（增强版）'!A2="","",F2-E2+1) -> 5 | H2: =IF('事件总表（增强版）'!F2="","",'事件总表（增强版）'!F2) -> 中 | I2: =IF(H2="高",3,IF(H2="中",2,IF(H2="低",1,""))) -> 2 | J2: =IF('事件总表（增强版）'!G2="","",'事件总表（增强版）'!G2) -> 正面 | K2: =IF(J2="正面",1,IF(J2="负面",-1,IF(J2="双向",0,""))) -> 1 | L2: 2 | M2: =IF(C2="宏观/地缘",1,0) -> 1 | N2: =IF(C2="行业/技术",1,0) -> 0 | O2: =IF(C2="政策",1,0) -> 0 | S2: 5.6 | T2: 已填代理CAR，可做初步相关性
A3: =IF('事件总表（增强版）'!A3="","",ROW()-1) -> 2 | B3: =IF('事件总表（增强版）'!A3="","",'事件总表（增强版）'!A3) -> 红海危机与A股航运板块联动 | C3: =IF('事件总表（增强版）'!B3="","",'事件总表（增强版）'!B3) -> 宏观/地缘 | D3: =IF('事件总表（增强版）'!C3="","",'事件总表（增强版）'!C3) -> 2023-12-18 | E3: =IF('事件总表（增强版）'!D3="","",'事件总表（增强版）'!D3) -> -1 | F3: =IF('事件总表（增强版）'!E3="","",'事件总表（增强版）'!E3) -> 3 | G3: =IF('事件总表（增强版）'!A3="","",F3-E3+1) -> 5 | H3: =IF('事件总表（增强版）'!F3="","",'事件总表（增强版）'!F3) -> 中 | I3: =IF(H3="高",3,IF(H3="中",2,IF(H3="低",1,""))) -> 2 | J3: =IF('事件总表（增强版）'!G3="","",'事件总表（增强版）'!G3) -> 正面 | K3: =IF(J3="正面",1,IF(J3="负面",-1,IF(J3="双向",0,""))) -> 1 | L3: 2 | M3: =IF(C3="宏观/地缘",1,0) -> 1 | N3: =IF(C3="行业/技术",1,0) -> 0 | O3: =IF(C3="政策",1,0) -> 0 | S3: 3.8 | T3: 已填代理CAR，可做初步相关性
A4: =IF('事件总表（增强版）'!A4="","",ROW()-1) -> 3 | B4: =IF('事件总表（增强版）'!A4="","",'事件总表（增强版）'!A4) -> 镓锗出口管制与A股稀有金属板块联动 | C4: =IF('事件总表（增强版）'!B4="","",'事件总表（增强版）'!B4) -> 宏观/地缘 | D4: =IF('事件总表（增强版）'!C4="","",'事件总表（增强版）'!C4) -> 2023-07-03 | E4: =IF('事件总表（增强版）'!D4="","",'事件总表（增强版）'!D4) -> -1 | F4: =IF('事件总表（增强版）'!E4="","",'事件总表（增强版）'!E4) -> 3 | G4: =IF('事件总表（增强版）'!A4="","",F4-E4+1) -> 5 | H4: =IF('事件总表（增强版）'!F4="","",'事件总表（增强版）'!F4) -> 中 | I4: =IF(H4="高",3,IF(H4="中",2,IF(H4="低",1,""))) -> 2 | J4: =IF('事件总表（增强版）'!G4="","",'事件总表（增强版）'!G4) -> 正面 | K4: =IF(J4="正面",1,IF(J4="负面",-1,IF(J4="双向",0,""))) -> 1 | L4: 2 | M4: =IF(C4="宏观/地缘",1,0) -> 1 | N4: =IF(C4="行业/技术",1,0) -> 0 | O4: =IF(C4="政策",1,0) -> 0 | S4: 4.5 | T4: 已填代理CAR，可做初步相关性
A5: =IF('事件总表（增强版）'!A5="","",ROW()-1) -> 4 | B5: =IF('事件总表（增强版）'!A5="","",'事件总表（增强版）'!A5) -> 锑及超硬材料出口管制与A股锑矿板块联动 | C5: =IF('事件总表（增强版）'!B5="","",'事件总表（增强版）'!B5) -> 宏观/地缘 | D5: =IF('事件总表（增强版）'!C5="","",'事件总表（增强版）'!C5) -> 2024-08-15 | E5: =IF('事件总表（增强版）'!D5="","",'事件总表（增强版）'!D5) -> -1 | F5: =IF('事件总表（增强版）'!E5="","",'事件总表（增强版）'!E5) -> 3 | G5: =IF('事件总表（增强版）'!A5="","",F5-E5+1) -> 5 | H5: =IF('事件总表（增强版）'!F5="","",'事件总表（增强版）'!F5) -> 中 | I5: =IF(H5="高",3,IF(H5="中",2,IF(H5="低",1,""))) -> 2 | J5: =IF('事件总表（增强版）'!G5="","",'事件总表（增强版）'!G5) -> 正面 | K5: =IF(J5="正面",1,IF(J5="负面",-1,IF(J5="双向",0,""))) -> 1 | L5: 2 | M5: =IF(C5="宏观/地缘",1,0) -> 1 | N5: =IF(C5="行业/技术",1,0) -> 0 | O5: =IF(C5="政策",1,0) -> 0 | S5: 3.7 | T5: 已填代理CAR，可做初步相关性
A6: =IF('事件总表（增强版）'!A6="","",ROW()-1) -> 5 | B6: =IF('事件总表（增强版）'!A6="","",'事件总表（增强版）'!A6) -> 超长期特别国债首发与A股基建板块联动 | C6: =IF('事件总表（增强版）'!B6="","",'事件总表（增强版）'!B6) -> 宏观/地缘 | D6: =IF('事件总表（增强版）'!C6="","",'事件总表（增强版）'!C6) -> 2024-05-17 | E6: =IF('事件总表（增强版）'!D6="","",'事件总表（增强版）'!D6) -> -1 | F6: =IF('事件总表（增强版）'!E6="","",'事件总表（增强版）'!E6) -> 3 | G6: =IF('事件总表（增强版）'!A6="","",F6-E6+1) -> 5 | H6: =IF('事件总表（增强版）'!F6="","",'事件总表（增强版）'!F6) -> 低 | I6: =IF(H6="高",3,IF(H6="中",2,IF(H6="低",1,""))) -> 1 | J6: =IF('事件总表（增强版）'!G6="","",'事件总表（增强版）'!G6) -> 正面 | K6: =IF(J6="正面",1,IF(J6="负面",-1,IF(J6="双向",0,""))) -> 1 | L6: 1 | M6: =IF(C6="宏观/地缘",1,0) -> 1 | N6: =IF(C6="行业/技术",1,0) -> 0 | O6: =IF(C6="政策",1,0) -> 0 | S6: 1.4 | T6: 已填代理CAR，可做初步相关性
A7: =IF('事件总表（增强版）'!A7="","",ROW()-1) -> 6 | B7: =IF('事件总表（增强版）'!A7="","",'事件总表（增强版）'!A7) -> 日本福岛核污染水排海与A股水产养殖联动 | C7: =IF('事件总表（增强版）'!B7="","",'事件总表（增强版）'!B7) -> 宏观/地缘 | D7: =IF('事件总表（增强版）'!C7="","",'事件总表（增强版）'!C7) -> 2023-08-24 | E7: =IF('事件总表（增强版）'!D7="","",'事件总表（增强版）'!D7) -> -1 | F7: =IF('事件总表（增强版）'!E7="","",'事件总表（增强版）'!E7) -> 3 | G7: =IF('事件总表（增强版）'!A7="","",F7-E7+1) -> 5 | H7: =IF('事件总表（增强版）'!F7="","",'事件总表（增强版）'!F7) -> 高 | I7: =IF(H7="高",3,IF(H7="中",2,IF(H7="低",1,""))) -> 3 | J7: =IF('事件总表（增强版）'!G7="","",'事件总表（增强版）'!G7) -> 正面 | K7: =IF(J7="正面",1,IF(J7="负面",-1,IF(J7="双向",0,""))) -> 1 | L7: 3 | M7: =IF(C7="宏观/地缘",1,0) -> 1 | N7: =IF(C7="行业/技术",1,0) -> 0 | O7: =IF(C7="政策",1,0) -> 0 | S7: 6.8 | T7: 已填代理CAR，可做初步相关性
A8: =IF('事件总表（增强版）'!A8="","",ROW()-1) -> 7 | B8: =IF('事件总表（增强版）'!A8="","",'事件总表（增强版）'!A8) -> 低空经济写入政府工作报告与飞行汽车板块联动 | C8: =IF('事件总表（增强版）'!B8="","",'事件总表（增强版）'!B8) -> 宏观/地缘 | D8: =IF('事件总表（增强版）'!C8="","",'事件总表（增强版）'!C8) -> 2024-03-29 | E8: =IF('事件总表（增强版）'!D8="","",'事件总表（增强版）'!D8) -> -1 | F8: =IF('事件总表（增强版）'!E8="","",'事件总表（增强版）'!E8) -> 3 | G8: =IF('事件总表（增强版）'!A8="","",F8-E8+1) -> 5 | H8: =IF('事件总表（增强版）'!F8="","",'事件总表（增强版）'!F8) -> 中 | I8: =IF(H8="高",3,IF(H8="中",2,IF(H8="低",1,""))) -> 2 | J8: =IF('事件总表（增强版）'!G8="","",'事件总表（增强版）'!G8) -> 正面 | K8: =IF(J8="正面",1,IF(J8="负面",-1,IF(J8="双向",0,""))) -> 1 | L8: 2 | M8: =IF(C8="宏观/地缘",1,0) -> 1 | N8: =IF(C8="行业/技术",1,0) -> 0 | O8: =IF(C8="政策",1,0) -> 0 | S8: 5.2 | T8: 已填代理CAR，可做初步相关性
A9: =IF('事件总表（增强版）'!A9="","",ROW()-1) -> 8 | B9: =IF('事件总表（增强版）'!A9="","",'事件总表（增强版）'!A9) -> 中央汇金买入ETF与A股宽基指数联动 | C9: =IF('事件总表（增强版）'!B9="","",'事件总表（增强版）'!B9) -> 宏观/地缘 | D9: =IF('事件总表（增强版）'!C9="","",'事件总表（增强版）'!C9) -> 2023-10-24 | E9: =IF('事件总表（增强版）'!D9="","",'事件总表（增强版）'!D9) -> -1 | F9: =IF('事件总表（增强版）'!E9="","",'事件总表（增强版）'!E9) -> 3 | G9: =IF('事件总表（增强版）'!A9="","",F9-E9+1) -> 5 | H9: =IF('事件总表（增强版）'!F9="","",'事件总表（增强版）'!F9) -> 低 | I9: =IF(H9="高",3,IF(H9="中",2,IF(H9="低",1,""))) -> 1 | J9: =IF('事件总表（增强版）'!G9="","",'事件总表（增强版）'!G9) -> 正面 | K9: =IF(J9="正面",1,IF(J9="负面",-1,IF(J9="双向",0,""))) -> 1 | L9: 1 | M9: =IF(C9="宏观/地缘",1,0) -> 1 | N9: =IF(C9="行业/技术",1,0) -> 0 | O9: =IF(C9="政策",1,0) -> 0 | S9: 1.8 | T9: 已填代理CAR，可做初步相关性
A10: =IF('事件总表（增强版）'!A10="","",ROW()-1) -> 9 | B10: =IF('事件总表（增强版）'!A10="","",'事件总表（增强版）'!A10) -> 中东地缘局势升级与A股避险板块联动 | C10: =IF('事件总表（增强版）'!B10="","",'事件总表（增强版）'!B10) -> 宏观/地缘 | D10: =IF('事件总表（增强版）'!C10="","",'事件总表（增强版）'!C10) -> 2024-04-15 | E10: =IF('事件总表（增强版）'!D10="","",'事件总表（增强版）'!D10) -> -1 | F10: =IF('事件总表（增强版）'!E10="","",'事件总表（增强版）'!E10) -> 3 | G10: =IF('事件总表（增强版）'!A10="","",F10-E10+1) -> 5 | H10: =IF('事件总表（增强版）'!F10="","",'事件总表（增强版）'!F10) -> 中 | I10: =IF(H10="高",3,IF(H10="中",2,IF(H10="低",1,""))) -> 2 | J10: =IF('事件总表（增强版）'!G10="","",'事件总表（增强版）'!G10) -> 正面 | K10: =IF(J10="正面",1,IF(J10="负面",-1,IF(J10="双向",0,""))) -> 1 | L10: 2 | M10: =IF(C10="宏观/地缘",1,0) -> 1 | N10: =IF(C10="行业/技术",1,0) -> 0 | O10: =IF(C10="政策",1,0) -> 0 | S10: 3.2 | T10: 已填代理CAR，可做初步相关性
A11: =IF('事件总表（增强版）'!A11="","",ROW()-1) -> 10 | B11: =IF('事件总表（增强版）'!A11="","",'事件总表（增强版）'!A11) -> CrowdStrike全球宕机与A股网安板块联动 | C11: =IF('事件总表（增强版）'!B11="","",'事件总表（增强版）'!B11) -> 宏观/地缘 | D11: =IF('事件总表（增强版）'!C11="","",'事件总表（增强版）'!C11) -> 2024-07-19 | E11: =IF('事件总表（增强版）'!D11="","",'事件总表（增强版）'!D11) -> -1 | F11: =IF('事件总表（增强版）'!E11="","",'事件总表（增强版）'!E11) -> 3 | G11: =IF('事件总表（增强版）'!A11="","",F11-E11+1) -> 5 | H11: =IF('事件总表（增强版）'!F11="","",'事件总表（增强版）'!F11) -> 中 | I11: =IF(H11="高",3,IF(H11="中",2,IF(H11="低",1,""))) -> 2 | J11: =IF('事件总表（增强版）'!G11="","",'事件总表（增强版）'!G11) -> 正面 | K11: =IF(J11="正面",1,IF(J11="负面",-1,IF(J11="双向",0,""))) -> 1 | L11: 2 | M11: =IF(C11="宏观/地缘",1,0) -> 1 | N11: =IF(C11="行业/技术",1,0) -> 0 | O11: =IF(C11="政策",1,0) -> 0 | S11: 2.6 | T11: 已填代理CAR，可做初步相关性
A12: =IF('事件总表（增强版）'!A12="","",ROW()-1) -> 11 | B12: =IF('事件总表（增强版）'!A12="","",'事件总表（增强版）'!A12) -> 中国对6国单方面免签与A股旅游航空联动 | C12: =IF('事件总表（增强版）'!B12="","",'事件总表（增强版）'!B12) -> 宏观/地缘 | D12: =IF('事件总表（增强版）'!C12="","",'事件总表（增强版）'!C12) -> 2023-11-24 | E12: =IF('事件总表（增强版）'!D12="","",'事件总表（增强版）'!D12) -> -1 | F12: =IF('事件总表（增强版）'!E12="","",'事件总表（增强版）'!E12) -> 3 | G12: =IF('事件总表（增强版）'!A12="","",F12-E12+1) -> 5 | H12: =IF('事件总表（增强版）'!F12="","",'事件总表（增强版）'!F12) -> 低 | I12: =IF(H12="高",3,IF(H12="中",2,IF(H12="低",1,""))) -> 1 | J12: =IF('事件总表（增强版）'!G12="","",'事件总表（增强版）'!G12) -> 正面 | K12: =IF(J12="正面",1,IF(J12="负面",-1,IF(J12="双向",0,""))) -> 1 | L12: 1 | M12: =IF(C12="宏观/地缘",1,0) -> 1 | N12: =IF(C12="行业/技术",1,0) -> 0 | O12: =IF(C12="政策",1,0) -> 0 | S12: 1.5 | T12: 已填代理CAR，可做初步相关性
A13: =IF('事件总表（增强版）'!A13="","",ROW()-1) -> 12 | B13: =IF('事件总表（增强版）'!A13="","",'事件总表（增强版）'!A13) -> 欧盟对华电动车反补贴调查与A股汽车出海联动 | C13: =IF('事件总表（增强版）'!B13="","",'事件总表（增强版）'!B13) -> 宏观/地缘 | D13: =IF('事件总表（增强版）'!C13="","",'事件总表（增强版）'!C13) -> 2023-10-04 | E13: =IF('事件总表（增强版）'!D13="","",'事件总表（增强版）'!D13) -> -1 | F13: =IF('事件总表（增强版）'!E13="","",'事件总表（增强版）'!E13) -> 3 | G13: =IF('事件总表（增强版）'!A13="","",F13-E13+1) -> 5 | H13: =IF('事件总表（增强版）'!F13="","",'事件总表（增强版）'!F13) -> 低 | I13: =IF(H13="高",3,IF(H13="中",2,IF(H13="低",1,""))) -> 1 | J13: =IF('事件总表（增强版）'!G13="","",'事件总表（增强版）'!G13) -> 负面 | K13: =IF(J13="正面",1,IF(J13="负面",-1,IF(J13="双向",0,""))) -> -1 | L13: -1 | M13: =IF(C13="宏观/地缘",1,0) -> 1 | N13: =IF(C13="行业/技术",1,0) -> 0 | O13: =IF(C13="政策",1,0) -> 0 | S13: -2.2 | T13: 已填代理CAR，可做初步相关性
... A100: =IF('事件总表（增强版）'!A100="","",ROW()-1) -> 99 | B100: =IF('事件总表（增强版）'!A100="","",'事件总表（增强版）'!A100) -> 潍柴动力一季报预增大幅提振商用车 | C100: =IF('事件总表（增强版）'!B100="","",'事件总表（增强版）'!B100) -> 公司行为 | D100: =IF('事件总表（增强版）'!C100="","",'事件总表（增强版）'!C100) -> 2024-04-08 | E100: =IF('事件总表（增强版）'!D100="","",'事件总表（增强版）'!D100) -> -1 | F100: =IF('事件总表（增强版）'!E100="","",'事件总表（增强版）'!E100) -> 3 | G100: =IF('事件总表（增强版）'!A100="","",F100-E100+1) -> 5 | H100: =IF('事件总表（增强版）'!F100="","",'事件总表（增强版）'!F100) -> 中 | I100: =IF(H100="高",3,IF(H100="中",2,IF(H100="低",1,""))) -> 2 | J100: =IF('事件总表（增强版）'!G100="","",'事件总表（增强版）'!G100) -> 正面 | K100: =IF(J100="正面",1,IF(J100="负面",-1,IF(J100="双向",0,""))) -> 1 | L100: 2 | M100: =IF(C100="宏观/地缘",1,0) -> 0 | N100: =IF(C100="行业/技术",1,0) -> 0 | O100: =IF(C100="政策",1,0) -> 0 | S100: 5 | T100: 已填代理CAR，可做初步相关性

Sheet 相关性分析
A1: 相关性分析：事件量化特征与代理CAR的关系
A2: 说明：本表S列已先填入“代理CAR(%)”，它是根据事件描述、已知涨幅表述、影响强度和影响方向估算的初稿值，不等同于用个股/板块日收益和市场模型计算出的真实CAR。正式论文建议后续用行情数据重新核验。
A6: 变量 | B6: 特征列 | C6: 含义 | D6: Pearson r | E6: 有效样本n | F6: t统计量 | G6: p值 | H6: 显著性 | I6: 结论
A7: 强度得分 | B7: I | C7: 高=3、中=2、低=1，衡量事件冲击强弱 | D7: 0.6425 | E7: 99 | F7: 8.2581 | G7: 0 | H7: 显著 | I7: 正相关，显著（代理CAR口径）
A8: 方向得分 | B8: K | C8: 正面=1、负面=-1、双向=0，衡量事件方向 | D8: 0.2985 | E8: 99 | F8: 3.0807 | G8: 0.0027 | H8: 显著 | I8: 正相关，显著（代理CAR口径）
A9: 综合影响得分 | B9: L | C9: 强度得分×方向得分，同时考虑方向和强弱 | D9: 0.6704 | E9: 99 | F9: 8.8982 | G9: 0 | H9: 显著 | I9: 正相关，显著（代理CAR口径）
A10: 窗口长度 | B10: G | C10: 事件窗口天数，反映市场反应观察周期 | D10: -0.3166 | E10: 99 | F10: -3.2877 | G10: 0.0014 | H10: 显著 | I10: 负相关，显著（代理CAR口径）
A11: 宏观/地缘 | B11: M | C11: 事件类型虚拟变量：宏观/地缘=1，否则=0 | D11: -0.2338 | E11: 99 | F11: -2.3678 | G11: 0.0199 | H11: 显著 | I11: 负相关，显著（代理CAR口径）
A12: 行业/技术 | B12: N | C12: 事件类型虚拟变量：行业/技术=1，否则=0 | D12: 0.0485 | E12: 99 | F12: 0.4779 | G12: 0.6338 | H12: 不显著 | I12: 正相关，不显著（代理CAR口径）
A13: 政策 | B13: O | C13: 事件类型虚拟变量：政策=1，否则=0 | D13: -0.3747 | E13: 99 | F13: -3.9808 | G13: 0.0001 | H13: 显著 | I13: 负相关，显著（代理CAR口径）
A14: 新闻发布量 | B14: P | C14: 未补充：公告/新闻数量，可继续补充后再算 | D14: 未填特征 | E14: 0 | H14: 待填 | I14: 样本不足或变量无差异，不能判断
A15: 舆情热度 | B15: Q | C15: 未补充：热搜/讨论度/媒体关注度等 | D15: 未填特征 | E15: 0 | H15: 待填 | I15: 样本不足或变量无差异，不能判断
A16: 情感倾向 | B16: R | C16: 未补充：新闻情感分，建议正面=1、中性=0、负面=-1 | D16: 未填特征 | E16: 0 | H16: 待填 | I16: 样本不足或变量无差异，不能判断
A19: 分组检验辅助表：补齐CAR后自动比较不同类型/方向/强度的平均异常收益
A21: 分组维度 | B21: 分组值 | C21: 有效样本n | D21: 平均代理CAR(%) | E21: 中位数代理CAR(%) | F21: 正CAR比例 | G21: 解释 | H21: 可写入论文的判断
A22: 影响强度 | B22: 高 | C22: 24 | D22: 9.98 | E22: 8.65 | F22: 1 | G22: 高强度事件的市场反应 | H22: 平均代理CAR较高，市场反应较强
A23: 影响强度 | B23: 中 | C23: 32 | D23: 4.31 | E23: 4.35 | F23: 0.97 | G23: 中等强度事件的市场反应 | H23: 平均代理CAR较高，市场反应较强
A24: 影响强度 | B24: 低 | C24: 43 | D24: 1.81 | E24: 1.5 | F24: 0.95 | G24: 低强度事件的市场反应 | H24: 平均代理CAR为正，市场反应偏正
A25: 影响方向 | B25: 正面 | C25: 95 | D25: 4.89 | E25: 3.8 | F25: 1 | G25: 正面事件对应的CAR | H25: 平均代理CAR较高，市场反应较强
A26: 影响方向 | B26: 负面 | C26: 3 | D26: -3.3 | E26: -3.5 | F26: 0 | G26: 负面事件对应的CAR | H26: 平均代理CAR为负，市场反应偏负
A27: 影响方向 | B27: 双向 | C27: 1 | D27: 0.6 | E27: 0.6 | F27: 1 | G27: 双向事件对应的CAR | H27: 平均代理CAR为正，市场反应偏正
A28: 事件类型 | B28: 宏观/地缘 | C28: 25 | D28: 2.63 | E28: 3.1 | F28: 0.88 | G28: 宏观/地缘事件的CAR | H28: 平均代理CAR为正，市场反应偏正
A29: 事件类型 | B29: 行业/技术 | C29: 25 | D29: 5.01 | E29: 4 | F29: 1 | G29: 行业/技术事件的CAR | H29: 平均代理CAR较高，市场反应较强
A30: 事件类型 | B30: 政策 | C30: 24 | D30: 1.36 | E30: 1.35 | F30: 1 | G30: 政策类事件的CAR | H30: 平均代理CAR为正，市场反应偏正
A31: 事件类型 | B31: 公司行为 | C31: 25 | D31: 9.27 | E31: 8 | F31: 1 | G31: 公司行为事件的CAR | H31: 平均代理CAR较高，市场反应较强
B35: 强度得分 | C35: 方向得分 | D35: 综合影响 | E35: 窗口长度 | F35: 新闻量 | G35: 舆情热度 | H35: 情感倾向 | I35: CAR
A36: 强度得分 | B36: =IF(SUMPRODUCT(--ISNUMBER(特征矩阵!$I$2:$I$100),--ISNUMBER(特征矩阵!$I$2:$I$100))<3,"",CORREL(特征矩阵!$I$2:$I$100,特征矩阵!$I$2:$I$100)) -> 1 | C36: =IF(SUMPRODUCT(--ISNUMBER(特征矩阵!$I$2:$I$100),--ISNUMBER(特征矩阵!$K$2:$K$100))<3,"",CORREL(特征矩阵!$I$2:$I$100,特征矩阵!$K$2:$K$100)) -> 0.12991079 | D36: =IF(SUMPRODUCT(--ISNUMBER(特征矩阵!$I$2:$I$100),--ISNUMBER(特征矩阵!$L$2:$L$100))<3,"",CORREL(特征矩阵!$I$2:$I$100,特征矩阵!$L$2:$L$100)) -> 0.86299744 | E36: =IF(SUMPRODUCT(--ISNUMBER(特征矩阵!$I$2:$I$100),--ISNUMBER(特征矩阵!$G$2:$G$100))<3,"",CORREL(特征矩阵!$I$2:$I$100,特征矩阵!$G$2:$G$100)) -> -0.45077269 | F36: =IF(SUMPRODUCT(--ISNUMBER(特征矩阵!$I$2:$I$100),--ISNUMBER(特征矩阵!$P$2:$P$100))<3,"",CORREL(特征矩阵!$I$2:$I$100,特征矩阵!$P$2:$P$100)) | G36: =IF(SUMPRODUCT(--ISNUMBER(特征矩阵!$I$2:$I$100),--ISNUMBER(特征矩阵!$Q$2:$Q$100))<3,"",CORREL(特征矩阵!$I$2:$I$100,特征矩阵!$Q$2:$Q$100)) | H36: =IF(SUMPRODUCT(--ISNUMBER(特征矩阵!$I$2:$I$100),--ISNUMBER(特征矩阵!$R$2:$R$100))<3,"",CORREL(特征矩阵!$I$2:$I$100,特征矩阵!$R$2:$R$100)) | I36: =IF(SUMPRODUCT(--ISNUMBER(特征矩阵!$I$2:$I$100),--ISNUMBER(特征矩阵!$S$2:$S$100))<3,"",CORREL(特征矩阵!$I$2:$I$100,特征矩阵!$S$2:$S$100)) -> 0.64251181
A37: 方向得分 | B37: =IF(SUMPRODUCT(--ISNUMBER(特征矩阵!$K$2:$K$100),--ISNUMBER(特征矩阵!$I$2:$I$100))<3,"",CORREL(特征矩阵!$K$2:$K$100,特征矩阵!$I$2:$I$100)) -> 0.12991079 | C37: =IF(SUMPRODUCT(--ISNUMBER(特征矩阵!$K$2:$K$100),--ISNUMBER(特征矩阵!$K$2:$K$100))<3,"",CORREL(特征矩阵!$K$2:$K$100,特征矩阵!$K$2:$K$100)) -> 1 | D37: =IF(SUMPRODUCT(--ISNUMBER(特征矩阵!$K$2:$K$100),--ISNUMBER(特征矩阵!$L$2:$L$100))<3,"",CORREL(特征矩阵!$K$2:$K$100,特征矩阵!$L$2:$L$100)) -> 0.58368054 | E37: =IF(SUMPRODUCT(--ISNUMBER(特征矩阵!$K$2:$K$100),--ISNUMBER(特征矩阵!$G$2:$G$100))<3,"",CORREL(特征矩阵!$K$2:$K$100,特征矩阵!$G$2:$G$100)) -> 0.042762473 | F37: =IF(SUMPRODUCT(--ISNUMBER(特征矩阵!$K$2:$K$100),--ISNUMBER(特征矩阵!$P$2:$P$100))<3,"",CORREL(特征矩阵!$K$2:$K$100,特征矩阵!$P$2:$P$100)) | G37: =IF(SUMPRODUCT(--ISNUMBER(特征矩阵!$K$2:$K$100),--ISNUMBER(特征矩阵!$Q$2:$Q$100))<3,"",CORREL(特征矩阵!$K$2:$K$100,特征矩阵!$Q$2:$Q$100)) | H37: =IF(SUMPRODUCT(--ISNUMBER(特征矩阵!$K$2:$K$100),--ISNUMBER(特征矩阵!$R$2:$R$100))<3,"",CORREL(特征矩阵!$K$2:$K$100,特征矩阵!$R$2:$R$100)) | I37: =IF(SUMPRODUCT(--ISNUMBER(特征矩阵!$K$2:$K$100),--ISNUMBER(特征矩阵!$S$2:$S$100))<3,"",CORREL(特征矩阵!$K$2:$K$100,特征矩阵!$S$2:$S$100)) -> 0.29852973
A38: 综合影响 | B38: =IF(SUMPRODUCT(--ISNUMBER(特征矩阵!$L$2:$L$100),--ISNUMBER(特征矩阵!$I$2:$I$100))<3,"",CORREL(特征矩阵!$L$2:$L$100,特征矩阵!$I$2:$I$100)) -> 0.86299744 | C38: =IF(SUMPRODUCT(--ISNUMBER(特征矩阵!$L$2:$L$100),--ISNUMBER(特征矩阵!$K$2:$K$100))<3,"",CORREL(特征矩阵!$L$2:$L$100,特征矩阵!$K$2:$K$100)) -> 0.58368054 | D38: =IF(SUMPRODUCT(--ISNUMBER(特征矩阵!$L$2:$L$100),--ISNUMBER(特征矩阵!$L$2:$L$100))<3,"",CORREL(特征矩阵!$L$2:$L$100,特征矩阵!$L$2:$L$100)) -> 1 | E38: =IF(SUMPRODUCT(--ISNUMBER(特征矩阵!$L$2:$L$100),--ISNUMBER(特征矩阵!$G$2:$G$100))<3,"",CORREL(特征矩阵!$L$2:$L$100,特征矩阵!$G$2:$G$100)) -> -0.34986226 | F38: =IF(SUMPRODUCT(--ISNUMBER(特征矩阵!$L$2:$L$100),--ISNUMBER(特征矩阵!$P$2:$P$100))<3,"",CORREL(特征矩阵!$L$2:$L$100,特征矩阵!$P$2:$P$100)) | G38: =IF(SUMPRODUCT(--ISNUMBER(特征矩阵!$L$2:$L$100),--ISNUMBER(特征矩阵!$Q$2:$Q$100))<3,"",CORREL(特征矩阵!$L$2:$L$100,特征矩阵!$Q$2:$Q$100)) | H38: =IF(SUMPRODUCT(--ISNUMBER(特征矩阵!$L$2:$L$100),--ISNUMBER(特征矩阵!$R$2:$R$100))<3,"",CORREL(特征矩阵!$L$2:$L$100,特征矩阵!$R$2:$R$100)) | I38: =IF(SUMPRODUCT(--ISNUMBER(特征矩阵!$L$2:$L$100),--ISNUMBER(特征矩阵!$S$2:$S$100))<3,"",CORREL(特征矩阵!$L$2:$L$100,特征矩阵!$S$2:$S$100)) -> 0.67039009
A39: 窗口长度 | B39: =IF(SUMPRODUCT(--ISNUMBER(特征矩阵!$G$2:$G$100),--ISNUMBER(特征矩阵!$I$2:$I$100))<3,"",CORREL(特征矩阵!$G$2:$G$100,特征矩阵!$I$2:$I$100)) -> -0.45077269 | C39: =IF(SUMPRODUCT(--ISNUMBER(特征矩阵!$G$2:$G$100),--ISNUMBER(特征矩阵!$K$2:$K$100))<3,"",CORREL(特征矩阵!$G$2:$G$100,特征矩阵!$K$2:$K$100)) -> 0.042762473 | D39: =IF(SUMPRODUCT(--ISNUMBER(特征矩阵!$G$2:$G$100),--ISNUMBER(特征矩阵!$L$2:$L$100))<3,"",CORREL(特征矩阵!$G$2:$G$100,特征矩阵!$L$2:$L$100)) -> -0.34986226 | E39: =IF(SUMPRODUCT(--ISNUMBER(特征矩阵!$G$2:$G$100),--ISNUMBER(特征矩阵!$G$2:$G$100))<3,"",CORREL(特征矩阵!$G$2:$G$100,特征矩阵!$G$2:$G$100)) -> 1 | F39: =IF(SUMPRODUCT(--ISNUMBER(特征矩阵!$G$2:$G$100),--ISNUMBER(特征矩阵!$P$2:$P$100))<3,"",CORREL(特征矩阵!$G$2:$G$100,特征矩阵!$P$2:$P$100)) | G39: =IF(SUMPRODUCT(--ISNUMBER(特征矩阵!$G$2:$G$100),--ISNUMBER(特征矩阵!$Q$2:$Q$100))<3,"",CORREL(特征矩阵!$G$2:$G$100,特征矩阵!$Q$2:$Q$100)) | H39: =IF(SUMPRODUCT(--ISNUMBER(特征矩阵!$G$2:$G$100),--ISNUMBER(特征矩阵!$R$2:$R$100))<3,"",CORREL(特征矩阵!$G$2:$G$100,特征矩阵!$R$2:$R$100)) | I39: =IF(SUMPRODUCT(--ISNUMBER(特征矩阵!$G$2:$G$100),--ISNUMBER(特征矩阵!$S$2:$S$100))<3,"",CORREL(特征矩阵!$G$2:$G$100,特征矩阵!$S$2:$S$100)) -> -0.31664058
A40: 新闻量 | B40: =IF(SUMPRODUCT(--ISNUMBER(特征矩阵!$P$2:$P$100),--ISNUMBER(特征矩阵!$I$2:$I$100))<3,"",CORREL(特征矩阵!$P$2:$P$100,特征矩阵!$I$2:$I$100)) | C40: =IF(SUMPRODUCT(--ISNUMBER(特征矩阵!$P$2:$P$100),--ISNUMBER(特征矩阵!$K$2:$K$100))<3,"",CORREL(特征矩阵!$P$2:$P$100,特征矩阵!$K$2:$K$100)) | D40: =IF(SUMPRODUCT(--ISNUMBER(特征矩阵!$P$2:$P$100),--ISNUMBER(特征矩阵!$L$2:$L$100))<3,"",CORREL(特征矩阵!$P$2:$P$100,特征矩阵!$L$2:$L$100)) | E40: =IF(SUMPRODUCT(--ISNUMBER(特征矩阵!$P$2:$P$100),--ISNUMBER(特征矩阵!$G$2:$G$100))<3,"",CORREL(特征矩阵!$P$2:$P$100,特征矩阵!$G$2:$G$100)) | F40: =IF(SUMPRODUCT(--ISNUMBER(特征矩阵!$P$2:$P$100),--ISNUMBER(特征矩阵!$P$2:$P$100))<3,"",CORREL(特征矩阵!$P$2:$P$100,特征矩阵!$P$2:$P$100)) | G40: =IF(SUMPRODUCT(--ISNUMBER(特征矩阵!$P$2:$P$100),--ISNUMBER(特征矩阵!$Q$2:$Q$100))<3,"",CORREL(特征矩阵!$P$2:$P$100,特征矩阵!$Q$2:$Q$100)) | H40: =IF(SUMPRODUCT(--ISNUMBER(特征矩阵!$P$2:$P$100),--ISNUMBER(特征矩阵!$R$2:$R$100))<3,"",CORREL(特征矩阵!$P$2:$P$100,特征矩阵!$R$2:$R$100)) | I40: =IF(SUMPRODUCT(--ISNUMBER(特征矩阵!$P$2:$P$100),--ISNUMBER(特征矩阵!$S$2:$S$100))<3,"",CORREL(特征矩阵!$P$2:$P$100,特征矩阵!$S$2:$S$100))
A41: 舆情热度 | B41: =IF(SUMPRODUCT(--ISNUMBER(特征矩阵!$Q$2:$Q$100),--ISNUMBER(特征矩阵!$I$2:$I$100))<3,"",CORREL(特征矩阵!$Q$2:$Q$100,特征矩阵!$I$2:$I$100)) | C41: =IF(SUMPRODUCT(--ISNUMBER(特征矩阵!$Q$2:$Q$100),--ISNUMBER(特征矩阵!$K$2:$K$100))<3,"",CORREL(特征矩阵!$Q$2:$Q$100,特征矩阵!$K$2:$K$100)) | D41: =IF(SUMPRODUCT(--ISNUMBER(特征矩阵!$Q$2:$Q$100),--ISNUMBER(特征矩阵!$L$2:$L$100))<3,"",CORREL(特征矩阵!$Q$2:$Q$100,特征矩阵!$L$2:$L$100)) | E41: =IF(SUMPRODUCT(--ISNUMBER(特征矩阵!$Q$2:$Q$100),--ISNUMBER(特征矩阵!$G$2:$G$100))<3,"",CORREL(特征矩阵!$Q$2:$Q$100,特征矩阵!$G$2:$G$100)) | F41: =IF(SUMPRODUCT(--ISNUMBER(特征矩阵!$Q$2:$Q$100),--ISNUMBER(特征矩阵!$P$2:$P$100))<3,"",CORREL(特征矩阵!$Q$2:$Q$100,特征矩阵!$P$2:$P$100)) | G41: =IF(SUMPRODUCT(--ISNUMBER(特征矩阵!$Q$2:$Q$100),--ISNUMBER(特征矩阵!$Q$2:$Q$100))<3,"",CORREL(特征矩阵!$Q$2:$Q$100,特征矩阵!$Q$2:$Q$100)) | H41: =IF(SUMPRODUCT(--ISNUMBER(特征矩阵!$Q$2:$Q$100),--ISNUMBER(特征矩阵!$R$2:$R$100))<3,"",CORREL(特征矩阵!$Q$2:$Q$100,特征矩阵!$R$2:$R$100)) | I41: =IF(SUMPRODUCT(--ISNUMBER(特征矩阵!$Q$2:$Q$100),--ISNUMBER(特征矩阵!$S$2:$S$100))<3,"",CORREL(特征矩阵!$Q$2:$Q$100,特征矩阵!$S$2:$S$100))
A42: 情感倾向 | B42: =IF(SUMPRODUCT(--ISNUMBER(特征矩阵!$R$2:$R$100),--ISNUMBER(特征矩阵!$I$2:$I$100))<3,"",CORREL(特征矩阵!$R$2:$R$100,特征矩阵!$I$2:$I$100)) | C42: =IF(SUMPRODUCT(--ISNUMBER(特征矩阵!$R$2:$R$100),--ISNUMBER(特征矩阵!$K$2:$K$100))<3,"",CORREL(特征矩阵!$R$2:$R$100,特征矩阵!$K$2:$K$100)) | D42: =IF(SUMPRODUCT(--ISNUMBER(特征矩阵!$R$2:$R$100),--ISNUMBER(特征矩阵!$L$2:$L$100))<3,"",CORREL(特征矩阵!$R$2:$R$100,特征矩阵!$L$2:$L$100)) | E42: =IF(SUMPRODUCT(--ISNUMBER(特征矩阵!$R$2:$R$100),--ISNUMBER(特征矩阵!$G$2:$G$100))<3,"",CORREL(特征矩阵!$R$2:$R$100,特征矩阵!$G$2:$G$100)) | F42: =IF(SUMPRODUCT(--ISNUMBER(特征矩阵!$R$2:$R$100),--ISNUMBER(特征矩阵!$P$2:$P$100))<3,"",CORREL(特征矩阵!$R$2:$R$100,特征矩阵!$P$2:$P$100)) | G42: =IF(SUMPRODUCT(--ISNUMBER(特征矩阵!$R$2:$R$100),--ISNUMBER(特征矩阵!$Q$2:$Q$100))<3,"",CORREL(特征矩阵!$R$2:$R$100,特征矩阵!$Q$2:$Q$100)) | H42: =IF(SUMPRODUCT(--ISNUMBER(特征矩阵!$R$2:$R$100),--ISNUMBER(特征矩阵!$R$2:$R$100))<3,"",CORREL(特征矩阵!$R$2:$R$100,特征矩阵!$R$2:$R$100)) | I42: =IF(SUMPRODUCT(--ISNUMBER(特征矩阵!$R$2:$R$100),--ISNUMBER(特征矩阵!$S$2:$S$100))<3,"",CORREL(特征矩阵!$R$2:$R$100,特征矩阵!$S$2:$S$100))
A43: CAR | B43: =IF(SUMPRODUCT(--ISNUMBER(特征矩阵!$S$2:$S$100),--ISNUMBER(特征矩阵!$I$2:$I$100))<3,"",CORREL(特征矩阵!$S$2:$S$100,特征矩阵!$I$2:$I$100)) -> 0.64251181 | C43: =IF(SUMPRODUCT(--ISNUMBER(特征矩阵!$S$2:$S$100),--ISNUMBER(特征矩阵!$K$2:$K$100))<3,"",CORREL(特征矩阵!$S$2:$S$100,特征矩阵!$K$2:$K$100)) -> 0.29852973 | D43: =IF(SUMPRODUCT(--ISNUMBER(特征矩阵!$S$2:$S$100),--ISNUMBER(特征矩阵!$L$2:$L$100))<3,"",CORREL(特征矩阵!$S$2:$S$100,特征矩阵!$L$2:$L$100)) -> 0.67039009 | E43: =IF(SUMPRODUCT(--ISNUMBER(特征矩阵!$S$2:$S$100),--ISNUMBER(特征矩阵!$G$2:$G$100))<3,"",CORREL(特征矩阵!$S$2:$S$100,特征矩阵!$G$2:$G$100)) -> -0.31664058 | F43: =IF(SUMPRODUCT(--ISNUMBER(特征矩阵!$S$2:$S$100),--ISNUMBER(特征矩阵!$P$2:$P$100))<3,"",CORREL(特征矩阵!$S$2:$S$100,特征矩阵!$P$2:$P$100)) | G43: =IF(SUMPRODUCT(--ISNUMBER(特征矩阵!$S$2:$S$100),--ISNUMBER(特征矩阵!$Q$2:$Q$100))<3,"",CORREL(特征矩阵!$S$2:$S$100,特征矩阵!$Q$2:$Q$100)) | H43: =IF(SUMPRODUCT(--ISNUMBER(特征矩阵!$S$2:$S$100),--ISNUMBER(特征矩阵!$R$2:$R$100))<3,"",CORREL(特征矩阵!$S$2:$S$100,特征矩阵!$R$2:$R$100)) | I43: =IF(SUMPRODUCT(--ISNUMBER(特征矩阵!$S$2:$S$100),--ISNUMBER(特征矩阵!$S$2:$S$100))<3,"",CORREL(特征矩阵!$S$2:$S$100,特征矩阵!$S$2:$S$100)) -> 1

Sheet 论文写法与Python代码
A1: 相关性分析写作与Python代码（可直接放论文/报告）
A14: 三、Python计算代码
A15: import pandas as pd
A16: from scipy import stats
A18: df = pd.read_excel('事件识别_相关性分析已补全.xlsx', sheet_name='特征矩阵')
A20: # 需要先保证“事件窗口CAR(%)（待填）”列已经填好
A21: target = '事件窗口CAR(%)（待填）'
A22: features = ['强度得分','方向得分','综合影响得分','窗口长度','宏观/地缘','行业/技术','政策','新闻发布量（待填）','舆情热度（待填）','情感倾向（待填）']
A24: rows = []
A25: for f in features:
A26: tmp = df[[f, target]].dropna()
A27: tmp = tmp[pd.to_numeric(tmp[f], errors='coerce').notna() & pd.to_numeric(tmp[target], errors='coerce').notna()]
... A38: print(result)
